adc_appkit/__init__.py
adc_appkit/base_app.py
adc_appkit/component_manager.py
adc_appkit/di_container.py
adc_appkit/py.typed
adc_appkit/request_scope.py
adc_appkit/components/__init__.py
adc_appkit/components/component.py
adc_appkit/components/http.py
adc_appkit/components/pg.py
adc_appkit/components/s3.py
adc_appkit-0.1.0.dist-info/METADATA
adc_appkit-0.1.0.dist-info/WHEEL
adc_appkit-0.1.0.dist-info/RECORD
