Metadata-Version: 2.4
Name: adc-appkit
Version: 0.1.0
Summary: ADC AppKit - библиотека для управления компонентами и состоянием приложения
Project-URL: Homepage, https://github.com/ascet-dev/adc-appkit
Project-URL: Repository, https://github.com/ascet-dev/adc-appkit
Project-URL: Documentation, https://github.com/ascet-dev/adc-appkit
Author-email: ADC Team <team@adc.dev>
License: MIT
Keywords: appkit,async,component,dependency-injection,di,lifecycle
Classifier: Development Status :: 4 - Beta
Classifier: Intended Audience :: Developers
Classifier: License :: OSI Approved :: MIT License
Classifier: Programming Language :: Python :: 3
Classifier: Programming Language :: Python :: 3.8
Classifier: Programming Language :: Python :: 3.9
Classifier: Programming Language :: Python :: 3.10
Classifier: Programming Language :: Python :: 3.11
Classifier: Programming Language :: Python :: 3.12
Requires-Python: >=3.8
Provides-Extra: dev
Requires-Dist: black>=22.0.0; extra == 'dev'
Requires-Dist: isort>=5.0.0; extra == 'dev'
Requires-Dist: mypy>=1.0.0; extra == 'dev'
Requires-Dist: pytest-asyncio>=0.21.0; extra == 'dev'
Requires-Dist: pytest>=7.0.0; extra == 'dev'
